od_standards_calibration_plugin/__init__.py
od_standards_calibration_plugin/od_calibration_from_standards.py
od_standards_calibration_plugin/ui/contrib/jobs/od_standards_calibration_plugin.yaml
od_standards_calibration_plugin-1.0.2.dist-info/LICENSE.txt
od_standards_calibration_plugin-1.0.2.dist-info/METADATA
od_standards_calibration_plugin-1.0.2.dist-info/WHEEL
od_standards_calibration_plugin-1.0.2.dist-info/entry_points.txt
od_standards_calibration_plugin-1.0.2.dist-info/top_level.txt
od_standards_calibration_plugin-1.0.2.dist-info/RECORD
