Metadata-Version: 2.1
Name: od-standards-calibration-plugin
Version: 1.0.2
Summary: Calibrate OD using a set of standards.
Home-page: https://github.com/odcambc/od_standards_calibration_plugin
Author: Chris Macdonald
Author-email: christian.macdonald@ucsf.edu
License: MIT
License-File: LICENSE.txt
